READemption-2.0.4.data/scripts/reademption
reademptionlib/__init__.py
reademptionlib/bamsorter.py
reademptionlib/controller.py
reademptionlib/coveragecalculator.py
reademptionlib/coveragecreator.py
reademptionlib/crossalignfilter.py
reademptionlib/deseq.py
reademptionlib/fasta.py
reademptionlib/fastq.py
reademptionlib/fragmentbuilder.py
reademptionlib/genewisequanti.py
reademptionlib/gff3.py
reademptionlib/parameterlog.py
reademptionlib/pathcreator.py
reademptionlib/polyaclipper.py
reademptionlib/projectcreator.py
reademptionlib/rawstatdata.py
reademptionlib/readaligner.py
reademptionlib/readalignerstats.py
reademptionlib/readalignerstatstable.py
reademptionlib/readprocessor.py
reademptionlib/segemehl.py
reademptionlib/vizalign.py
reademptionlib/vizdeseq.py
reademptionlib/vizgenequanti.py
reademptionlib/wiggle.py
tests/__init__.py
tests/readaligner.py
tests/test_all.py
tests/test_controller.py
tests/test_controller_coverage_paired_end_fragments_align_fragments.py
tests/test_controller_coverage_paired_end_fragments_align_no_fragments.py
tests/test_controller_coverage_paired_end_no_fragments_align_fragments.py
tests/test_controller_coverage_paired_end_no_fragments_align_no_fragments.py
tests/test_controller_coverage_paired_end_no_norm_fragments_align_fragments.py
tests/test_controller_coverage_paired_end_no_norm_fragments_align_no_fragments.py
tests/test_controller_deseq2_comparison.py
tests/test_controller_deseq2_project.py
tests/test_controller_deseq2_species.py
tests/test_controller_gene_quanti_paired_end_fragments_align_fragments.py
tests/test_controller_gene_quanti_paired_end_fragments_align_no_fragments.py
tests/test_controller_gene_quanti_paired_end_no_fragments_align_fragments.py
tests/test_controller_gene_quanti_paired_end_no_fragments_align_no_fragments.py
tests/test_controller_gene_quanti_paired_end_no_norm_fragments_align_fragments.py
tests/test_controller_gene_quanti_paired_end_no_norm_fragments_align_no_fragments.py
tests/test_controller_viz_align.py
READemption-2.0.4.dist-info/AUTHORS.rst
READemption-2.0.4.dist-info/LICENSE.txt
READemption-2.0.4.dist-info/METADATA
READemption-2.0.4.dist-info/WHEEL
READemption-2.0.4.dist-info/top_level.txt
READemption-2.0.4.dist-info/RECORD
