Metadata-Version: 2.1
Name: READemption
Version: 2.0.4
Summary: A RNA-Seq Analysis Pipeline
Home-page: 
Author: Konrad U. Förstner, Till Sauerwein
Author-email: konrad@foerstner.org
License: MIT License
Platform: UNKNOWN
Classifier: License :: OSI Approved :: MIT License
Classifier: Operating System :: POSIX
Classifier: Programming Language :: Python :: 3
Classifier: Topic :: Scientific/Engineering :: Bio-Informatics
License-File: LICENSE.txt
License-File: AUTHORS.rst
Requires-Dist: biopython (>=1.79)
Requires-Dist: matplotlib (>=3.5.2)
Requires-Dist: pandas (>=1.4.3)
Requires-Dist: pysam (>=0.19.1)
Requires-Dist: seaborn (>=0.11.2)
Requires-Dist: sphinx-argparse (>=0.2.5)
